{
  "name": "RABBIT-CAGE-BUG-83",
  "type": "bug",
  "title": "scope-guard.py: import sys done twice (line 20 module-level and line 83 inside function)",
  "status": "close",
  "priority": "low",
  "description": "hooks/scope-guard.py line 83 re-imports sys inside find_feature_path() despite the module-level import at line 20. Dead code. Remove the inner import. Minor lint.",
  "related_feature": "rabbit-cage",
  "filed": "2026-05-18T03:27:49Z",
  "filed_by": "rabbit-file",
  "closed": "2026-05-18T08:43:42Z",
  "history": [
    {
      "ts": "2026-05-18T03:27:49Z",
      "actor": "rabbit-file",
      "action": "opened",
      "note": "initial filing"
    },
    {
      "ts": "2026-05-18T08:43:42Z",
      "actor": "rabbit-file",
      "action": "closed",
      "note": "wave-4 cleanup; fixed in e10610a (impl) and 91f2c68 (tests)",
      "fix_commits": "e10610a42a526d926fac760b39ae1d86da7f7c06"
    }
  ],
  "commit_sha": "0e1b5a28b4070e04136208660f15cb6aae9b1adc"
}