{
  "name": "CONTRACT-BUG-11",
  "type": "bug",
  "title": "feature.json.schema.json tdd_state enum missing merged/deprecated allowed by validator",
  "status": "close",
  "priority": "medium",
  "description": "schemas/feature.json.schema.json declares tdd_state enum: [spec, test-red, impl, test-green, review]. scripts/validate-feature.py line 97 allows merged and deprecated additionally. Same mismatch in schemas/registry.json.schema.json. Align both.",
  "related_feature": "contract",
  "filed": "2026-05-18T03:01:24Z",
  "filed_by": "rabbit-file",
  "closed": "2026-05-18T08:32:39Z",
  "history": [
    {
      "ts": "2026-05-18T03:01:24Z",
      "actor": "rabbit-file",
      "action": "opened",
      "note": "initial filing"
    },
    {
      "ts": "2026-05-18T08:32:39Z",
      "actor": "rabbit-file",
      "action": "closed",
      "note": "fixed in TDD cycle",
      "fix_commits": "eae35f270bb84a6a14bb814bc57b9f08613f49a0"
    }
  ],
  "commit_sha": "8e839631d59fc22ce8857a2828163fdbe2108dde"
}